stac_processor_cli/__init__.py
stac_processor_cli/__main__.py
stac_processor_cli/app.py
stac_repository/__about__.py
stac_repository/__init__.py
stac_repository/backend.py
stac_repository/base_stac_commit.py
stac_repository/base_stac_repository.py
stac_repository/base_stac_transaction.py
stac_repository/job_report.py
stac_repository/processor.py
stac_repository/processors.py
stac_repository/stac_processor.py
stac_repository/file/__init__.py
stac_repository/file/file_stac_commit.py
stac_repository/file/file_stac_repository.py
stac_repository/file/file_stac_transaction.py
stac_repository/git/__init__.py
stac_repository/git/cache.py
stac_repository/git/git.py
stac_repository/git/git2.py
stac_repository/git/git_stac_commit.py
stac_repository/git/git_stac_config.py
stac_repository/git/git_stac_repository.py
stac_repository/git/git_stac_transaction.py
stac_repository/stac/__init__.py
stac_repository/stac/models.py
stac_repository/stac/stac_io.py
stac_repository/stac/utils.py
stac_repository_cli/__init__.py
stac_repository_cli/__main__.py
stac_repository_cli/app.py
stac_repository_cli/backends.py
stac_repository_cli/config.py
stac_repository_cli/print.py
stac_repository-0.0.6.dist-info/METADATA
stac_repository-0.0.6.dist-info/WHEEL
stac_repository-0.0.6.dist-info/entry_points.txt
stac_repository-0.0.6.dist-info/top_level.txt
stac_repository-0.0.6.dist-info/RECORD
