Metadata-Version: 2.1
Name: stac-repository
Version: 0.0.6
Summary: A (git-)versionned STAC catalog storage and management system
Author-email: Pierre Fontbonne <pierre.fontbonne@uca.fr>
Maintainer-email: Pierre Fontbonne <pierre.fontbonne@uca.fr>, Yannick Guéhenneux <yannick.guehenneux@uca.fr>
License: OPEN LICENCE 2.0/LICENCE OUVERTE 2.0
Project-URL: Homepage, https://github.com/fntb/stac-repository
Project-URL: Documentation, https://github.com/fntb/stac-repository
Project-URL: Repository, https://github.com/fntb/stac-repository
Project-URL: Issues, https://github.com/fntb/stac-repository
Keywords: pystac,stac,database,git,repository,storage,store
Classifier: Intended Audience :: Developers
Classifier: Intended Audience :: Information Technology
Classifier: Intended Audience :: Science/Research
Classifier: Programming Language :: Python :: 3.12
Classifier: Programming Language :: Python :: 3.11
Classifier: Programming Language :: Python :: 3.10
Classifier: Programming Language :: Python :: 3.9
Classifier: Programming Language :: Python :: 3.8
Classifier: Development Status :: 4 - Beta
Requires-Python: >=3.8
Requires-Dist: pydantic ~=2.10.3
Requires-Dist: stac-pydantic ~=3.2.0
Requires-Dist: orjson ~=3.10
Requires-Dist: shapely ~=2.0.0
Requires-Dist: typer ~=0.15.1
Requires-Dist: typing-extensions >=4.13.2
Requires-Dist: requests >=2.32.4
Requires-Dist: tomlkit >=0.13.3
